{
	"$schema": "https://tonytools.win/schemas/locr.schema.json",
	"hash": "00F38CC8EBC0E730",
	"languages": {
		"xx": {
			"D27065E2": "Welcome to the Hitman VR Tutorial.<br><br>Here you will learn all the basics of how to play Hitman in VR.",
			"75CC9B46": "",
			"FD6F166C": "Welcome to the VR playground. <br><br>Spend some time here to familiarize yourself with different weapons and firearms, and practice smashing and shooting. <br><br>Press the exit button when you are ready to leave.",
			"D33D60AD": "Firearms",
			"DF50FC53": "",
			"9D0EED74": "Priming",
			"08B4B92C": "When playing in VR, you have to prime items to be able to add damage with them. Hold {SHOOT} to prime your currenlty equipped item.",
			"D9A7D201": "VR Comfort",
			"59E44040": "When playing in VR, you can tweak your experience by adjusting the VR Comfort Settings.<br><br>Experiment with the settings while you play to find what fits you the best.",
			"1AD1C70C": "Pick up all the coins and holster them",
			"62BE6D2E": "Move your head to look at the orbs",
			"C394DB78": "Look around",
			"A31B1643": "Movement",
			"D843821F": "Use {MOVE} to move",
			"ABD38F06": "Move {CAMERA} to turn",
			"3E9F3799": "Turn",
			"7655B170": "Shoot",
			"240319A6": "Press {SHOOT} to fire weapon",
			"CAE8EAB0": "Hold {AIM} to activate item aim",
			"D8B9E452": "Move controller to aim item",
			"6A184CA1": "Throwing",
			"A7F5548B": "Press {SHOOT} to throw item",
			"761163D4": "Move your head down to hide behind cover",
			"139474EA": "Covers",
			"9A77C67E": "Press {PICKUP} to pick up fiberwire",
			"74EA7072": "Pick up",
			"6671F5BB": "Prime melee item",
			"8A2A959F": "Hold {SHOOT}  to prime equipped melee weapon",
			"92FA8413": "Hold {SHOOT}  to make a fist when barehanded",
			"4E4E6836": "Prime fist",
			"632CCAC2": "Hold {TAKE_DISGUISE} to interact",
			"B77AB613": "Interact",
			"63BE8BF6": "Stand still",
			"3D0EF624": "Get in position",
			"DFD45FC7": "",
			"535E1038": "Hold {SHOOT} to prime fiberwire",
			"E56FDBEE": "Prime fiberwire",
			"50CA5C11": "Fiberwire elimination",
			"03395FD3": "Fiberwire",
			"D45247EE": "Move primed fiberwire over target head and pull hard to eliminate",
			"BF7EF725": "Reach hand towards neck",
			"ECE52B82": "Shake controller to subdue faster",
			"1C48D01A": "Press {SHOOT} to subdue",
			"F31131FF": "Hold {SHOOT} to make a fist and move controller to punch",
			"8400C3CD": "Subdue",
			"85CF62CC": "Place yourself in the circle",
			"FCED7DC9": "Snap Neck",
			"CF6C27CA": "Move hands towards head of pacified target",
			"737D46D9": "Press {SHOOT} to snap neck",
			"B332DDDF": "Move your head around to look",
			"5EF261AF": "Look around",
			"996F6909": "Pick up",
			"899158B0": "Press {PICKUP} to pick up wrench",
			"C9674DC9": "Swing primed wrench to pacify guard",
			"A18FE02F": "Pacify",
			"39A089AD": "Drag body",
			"77F9744E": "Reach your hand towards body and press {PICKUP} to drag",
			"56482D73": "Dump body",
			"F00E6306": "Reach your hand towards closet and press {PICKUP} to dump dragged body",
			"11740956": "Press {PICKUP} to pick up pistol",
			"DAD82FB5": "Pick up",
			"0BD5A6CD": "Pick up",
			"6E54917D": "Press  {PICKUP} to pick up SMG",
			"C50BFEAB": "Shoot Vase",
			"FE1F667A": "Look through sight to aim and shoot vase",
			"EAC025F8": "Aim Assist",
			"E29EB3CE": "Squeeze {SHOOT} lightly to activate aim assist",
			"6F619B07": "Shoot",
			"A5E8FFF9": "Hit cube three times",
			"4A428E9E": "Press {PICKUP} to pick up sniper",
			"F8FEFD50": "Pick up",
			"2BAC2A10": "Sniper scope",
			"864695A6": "Move controller up towards your head to enter sniper scope",
			"8C0AF88C": "Move controller around to aim sniper scope at target",
			"4C45720E": "Sniper",
			"034AB547": "Eliminate three targets with sniper rifle",
			"21EBCDAA": "Drop",
			"E81F1E76": "Move controller away from head and press {PICKUP} to drop rifle",
			"1903D3D1": "Move controller away from head to exit scope",
			"1835D42E": "Sniper aiming",
			"537E9ABE": "Punch",
			"A8E1B692": "Move Wireless Controller when fist is primed to pacify guard",
			"AEAFC0F6": "Pick up",
			"C5A740C1": "Press {PICKUP} to pick up katana",
			"898E8954": "Slashing",
			"D79106A2": "Move controller when katana is primed to kill guard",
			"31D90D85": "Priming",
			"DE2548C2": "Hold {SHOOT} to prime katana",
			"D4F3DA8F": "Holster",
			"E7571AAF": "Move hand into chest orb",
			"33676692": "Press {PICKUP} to holster",
			"32035A8B": "Press {PICKUP} to drop",
			"36FB842F": "In VR, the Orb in front of your chest is where you holster and unholster items.",
			"8245B103": "Press {PICKUP} to pick up",
			"E126213F": "Move the camera up towards your head and aim at the window lock to scan",
			"C637A07E": "Move the camera up towards your head and aim at the body to scan",
			"073EFDA0": "Rotate your right hand to see current outfit and status",
			"0EF7F6D7": "Press {HOLSTER} to zoom in and {DROP} to zoom out",
			"AC030C7B": "Scope Zoom",
			"4A7FFCE5": "Move hand into chest orb and tap {PICKUP} to holster weapon",
			"795D2E4D": "Holster",
			"48E79F88": "Move controller to aim, press {SHOOT} to shoot.",
			"7C815C56": "Hold {INSTINCT} to activate Instinct.",
			"74D69893": "Press {INSTINCT} to activate Instinct.",
			"CEAB1B0E": "Hold {SHOOT} to prime",
			"629CB8A0": "The guards consider you a threat and want to place you under arrest. You can comply by lifting your hands and lure the guard closer, creating an opportunity to attack him or make a run for it.",
			"3D2F2356": "Move hand towards chest and tap {PICKUP} to holster items",
			"9F0007BD": "PH_BodyText",
			"D43865ED": "The game does not autosave when playing VR.<BR>You can manually save and load from the menu. Press {START} to enter the menu.",
			"6D895B31": "Press  {PREVIOUS_ITEM}  to open inventory and equip coin",
			"2FF06C31": "Press  {PREVIOUS_ITEM} or {NEXT_ITEM}  to open inventory and equip coin",
			"EBB0B836": "Inventory",
			"3B7DB31A": "Press {PICKUP}  to unholster",
			"DEAE1211": "Press {PICKUP}  to holster",
			"B4DD0057": "Press {PICKUP}  to holster",
			"E6D45031": "Press {PICKUP}  to unholster",
			"B87E123B": "",
			"FA0E0149": "Move hand into chest orb and tap  {PICKUP} to unholster crowbar",
			"C9AAC169": "Unholster",
			"252F7D35": "Drop",
			"E8D7842A": "Drop SMG on table by pressing {PICKUP}",
			"53971DD0": "Place",
			"A01CEAE9": "Hold out your arm and press {PICKUP} to drop item",
			"0D9BFEF0": "Hold {START} to reset your postition",
			"CFB4BF55": "Recenter",
			"21D05080": "Reload",
			"370D228E": "Press {ACTION-Y} to reload your firearm",
			"24918A76": "Press {RELOAD} to reload your firearm",
			"1FA146C9": "Open the door by pressing {ACTION}",
			"5B6818D9": "You can also open doors by touching them with your hand",
			"0278B54C": "Doors",
			"DEDCB3DE": "PH_Crouch_Text_Text",
			"C683B297": "PH_Hint",
			"57F92367": "Stand",
			"921350B3": "Hold {SHOOT} to prime wrench"
		},
		"en": {
			"D27065E2": "Welcome to the Hitman VR Tutorial.<br><br>Here you will learn all the basics of how to play Hitman in VR.",
			"75CC9B46": "",
			"FD6F166C": "Welcome to the VR playground. <br><br>Spend some time here to familiarize yourself with different weapons and firearms, and practice smashing and shooting. <br><br>Press the exit button when you are ready to leave.",
			"D33D60AD": "Firearms",
			"DF50FC53": "",
			"9D0EED74": "Priming",
			"08B4B92C": "When playing in VR, you have to prime items to be able to add damage with them. Hold {SHOOT} to prime your currently equipped item.",
			"D9A7D201": "VR Comfort",
			"59E44040": "When playing in VR, you can tweak your experience by adjusting the VR Comfort Settings.<br><br>Experiment with the settings while you play to find what fits you the best.",
			"1AD1C70C": "Pick up all the coins and holster them",
			"62BE6D2E": "Move your head to look at the orbs",
			"C394DB78": "Look around",
			"A31B1643": "Movement",
			"D843821F": "Use {MOVE} to move",
			"ABD38F06": "Move {CAMERA} to turn",
			"3E9F3799": "Turn",
			"7655B170": "Shoot",
			"240319A6": "Press {SHOOT} to fire weapon",
			"CAE8EAB0": "Hold {AIM} to activate item aim",
			"D8B9E452": "Move controller to aim item",
			"6A184CA1": "Throwing",
			"A7F5548B": "Press {SHOOT} to throw item",
			"761163D4": "Move your head down to hide behind cover",
			"139474EA": "Covers",
			"9A77C67E": "Press {PICKUP} to pick up fiberwire",
			"74EA7072": "Pick up",
			"6671F5BB": "Prime melee item",
			"8A2A959F": "Hold {SHOOT} to prime equipped melee weapon",
			"92FA8413": "Hold {SHOOT}  to make a fist when barehanded",
			"4E4E6836": "Prime fist",
			"632CCAC2": "Hold {TAKE_DISGUISE} to interact",
			"B77AB613": "Interact",
			"63BE8BF6": "Stand still",
			"3D0EF624": "Get in position",
			"DFD45FC7": "",
			"535E1038": "Hold {SHOOT} to prime fiberwire",
			"E56FDBEE": "Prime fiberwire",
			"50CA5C11": "Fiberwire elimination",
			"03395FD3": "Fiberwire",
			"D45247EE": "Move primed fiberwire over target head and pull hard to eliminate",
			"BF7EF725": "Reach hand towards neck",
			"ECE52B82": "Shake controller to subdue faster",
			"1C48D01A": "Press {SHOOT} to subdue",
			"F31131FF": "Hold {SHOOT} to make a fist and move controller to punch",
			"8400C3CD": "Subdue",
			"85CF62CC": "Place yourself in the circle",
			"FCED7DC9": "Snap Neck",
			"CF6C27CA": "Move hands towards head of pacified target",
			"737D46D9": "Press {SHOOT} to snap neck",
			"B332DDDF": "Move your head around to look",
			"5EF261AF": "Look around",
			"996F6909": "Pick up",
			"899158B0": "Press {PICKUP} to pick up wrench",
			"C9674DC9": "Swing primed wrench to pacify guard",
			"A18FE02F": "Pacify",
			"39A089AD": "Drag body",
			"77F9744E": "Reach your hand towards body and press {PICKUP} to drag",
			"56482D73": "Dump body",
			"F00E6306": "Reach your hand towards closet and press {PICKUP} to dump dragged body",
			"11740956": "Press {PICKUP} to pick up pistol",
			"DAD82FB5": "Pick up",
			"0BD5A6CD": "Pick up",
			"6E54917D": "Press {PICKUP} to pick up SMG",
			"C50BFEAB": "Shoot Vase",
			"FE1F667A": "Look through sight to aim and shoot vase",
			"EAC025F8": "Aim Assist",
			"E29EB3CE": "Squeeze {SHOOT} lightly to activate aim assist",
			"6F619B07": "Shoot",
			"A5E8FFF9": "Hit cube three times",
			"4A428E9E": "Press {PICKUP} to pick up sniper",
			"F8FEFD50": "Pick up",
			"2BAC2A10": "Sniper scope",
			"864695A6": "Move controller up towards your head to enter sniper scope",
			"8C0AF88C": "Move controller around to aim sniper scope at target",
			"4C45720E": "Sniper",
			"034AB547": "Eliminate three targets with sniper rifle",
			"21EBCDAA": "Drop",
			"E81F1E76": "Move controller away from head and press {PICKUP} to drop rifle",
			"1903D3D1": "Move controller away from head to exit scope",
			"1835D42E": "Sniper aiming",
			"537E9ABE": "Punch",
			"A8E1B692": "Move wireless controller when fist is primed to pacify guard",
			"AEAFC0F6": "Pick up",
			"C5A740C1": "Press  {PICKUP} to pick up katana",
			"898E8954": "Slashing",
			"D79106A2": "Move controller when katana is primed to kill guard",
			"31D90D85": "Priming",
			"DE2548C2": "Hold {SHOOT} to prime katana",
			"D4F3DA8F": "Holster",
			"E7571AAF": "Move hand into chest orb",
			"33676692": "Press {PICKUP} to holster",
			"32035A8B": "Press {PICKUP} to drop",
			"36FB842F": "In VR, the Orb in front of your chest is where you holster and unholster items.",
			"8245B103": "Press {PICKUP} to pick up",
			"E126213F": "Move the camera up towards your head and aim at the window lock to scan",
			"C637A07E": "Move the camera up towards your head and aim at the body to scan",
			"073EFDA0": "Rotate your right hand to see current outfit and status",
			"0EF7F6D7": "Press {HOLSTER} to zoom in and {DROP} to zoom out",
			"AC030C7B": "Scope Zoom",
			"4A7FFCE5": "Move hand into chest orb and press {PICKUP} to holster weapon",
			"795D2E4D": "Holster",
			"48E79F88": "Move controller to aim, press {SHOOT} to shoot.",
			"7C815C56": "Hold {INSTINCT} to activate Instinct.",
			"74D69893": "Press {INSTINCT} to activate Instinct.",
			"CEAB1B0E": "Hold {SHOOT} to prime",
			"629CB8A0": "The guards consider you a threat and want to place you under arrest. You can comply by lifting your hands and lure the guard closer, creating an opportunity to attack him or make a run for it.",
			"3D2F2356": "Move hand towards chest and press {PICKUP} to holster items",
			"9F0007BD": "The game does not autosave when playing VR.<BR>You can manually save and load from the menu.",
			"D43865ED": "The game does not autosave when playing VR.<BR>You can manually save and load from the menu. Press {START} to enter the menu.",
			"6D895B31": "Press {PREVIOUS_ITEM}  to open inventory and equip a coin",
			"2FF06C31": "Press  {PREVIOUS_ITEM} or {NEXT_ITEM}  to open inventory and equip a coin",
			"EBB0B836": "Inventory",
			"3B7DB31A": "Press {PICKUP}  to unholster",
			"DEAE1211": "Press {PICKUP}  to holster",
			"B4DD0057": "Press {PICKUP}  to holster",
			"E6D45031": "Press {PICKUP}  to unholster",
			"B87E123B": "",
			"FA0E0149": "Move hand into chest orb and press {PICKUP} to unholster coin",
			"C9AAC169": "Unholster",
			"252F7D35": "Drop",
			"E8D7842A": "Drop SMG on table by pressing {PICKUP}",
			"53971DD0": "Place",
			"A01CEAE9": "Hold out your arm and press {PICKUP} to drop item",
			"0D9BFEF0": "Hold {START} to reset your postition",
			"CFB4BF55": "Recenter",
			"21D05080": "Reload",
			"370D228E": "Press {ACTION-Y} to reload your firearm",
			"24918A76": "Press {RELOAD} to reload your firearm",
			"1FA146C9": "Open the door by pressing {ACTION}",
			"5B6818D9": "You can also open doors by touching them with your hand",
			"0278B54C": "Doors",
			"DEDCB3DE": "Press {CROUCH} to stand up",
			"C683B297": "Crouch",
			"57F92367": "Stand",
			"921350B3": "Hold {SHOOT} to prime wrench"
		},
		"fr": {
			"D27065E2": "Bienvenue dans l'initiation à la VR de Hitman.<br><br>Vous apprendrez ici les rudiments nécessaires pour jouer au jeu en VR.",
			"75CC9B46": "",
			"FD6F166C": "Bienvenue dans l'espace libre de VR.<br><br>Passez un peu de temps ici pour vous familiariser avec les différentes armes, le combat et le tir.<br><br>Appuyez sur le bouton de sortie quand vous avez terminé et que vous êtes prêt.",
			"D33D60AD": "Arme à feu",
			"DF50FC53": "",
			"9D0EED74": "Préparation",
			"08B4B92C": "Quand vous jouez en VR, vous devez préparer des objets pour leur permettre d'infliger des dégâts. Maintenez {SHOOT} pour préparer l'objet actuellement équipé.",
			"D9A7D201": "Confort de VR",
			"59E44040": "Quand vous jouez en VR, vous pouvez personnaliser votre expérience en ajustant les réglages de Confort de VR.<br><br>Essayez différents réglages en jeu pour savoir quelle configuration vous convient le mieux.",
			"1AD1C70C": "Prenez toutes les pièces et rangez-les",
			"62BE6D2E": "Bougez la tête pour regarder les orbes",
			"C394DB78": "Regarder autour de vous",
			"A31B1643": "Déplacements",
			"D843821F": "Utilisez {MOVE} pour vous déplacer",
			"ABD38F06": "Bougez {CAMERA} pour tourner",
			"3E9F3799": "Tourner",
			"7655B170": "Tirer",
			"240319A6": "Appuyez sur {SHOOT} pour tirer avec l'arme",
			"CAE8EAB0": "Maintenez {AIM} pour viser avec l'objet",
			"D8B9E452": "Bougez la manette pour viser avec l'objet",
			"6A184CA1": "Lancer",
			"A7F5548B": "Appuyez sur {SHOOT} pour lancer l'objet",
			"761163D4": "Baissez la tête pour vous mettre à couvert",
			"139474EA": "Se mettre à couvert",
			"9A77C67E": "Appuyez sur {PICKUP} pour prendre la corde de piano",
			"74EA7072": "Prendre",
			"6671F5BB": "Préparer des objets de corps à corps",
			"8A2A959F": "Maintenez {SHOOT} pour préparer une arme de corps à corps équipée",
			"92FA8413": "Maintenez {SHOOT} pour serrer le poing à mains nues",
			"4E4E6836": "Préparer un poing",
			"632CCAC2": "Maintenez {TAKE_DISGUISE} pour interagir",
			"B77AB613": "Interagir",
			"63BE8BF6": "Restez immobile",
			"3D0EF624": "Mettez-vous en position",
			"DFD45FC7": "",
			"535E1038": "Maintenez {SHOOT} pour préparer la corde de piano",
			"E56FDBEE": "Préparer la corde de piano",
			"50CA5C11": "Élimination à la corde de piano",
			"03395FD3": "Corde de piano",
			"D45247EE": "Déplacez la corde de piano préparée vers la tête de la cible et tirez fort pour l'éliminer",
			"BF7EF725": "Approchez vos mains du cou",
			"ECE52B82": "Secouez la manette pour maîtriser plus rapidement",
			"1C48D01A": "Appuyez sur {SHOOT} pour maîtriser",
			"F31131FF": "Maintenez {SHOOT} pour serrer le poing puis bougez la manette pour frapper",
			"8400C3CD": "Maîtriser",
			"85CF62CC": "Placez-vous dans le cercle",
			"FCED7DC9": "Briser le cou",
			"CF6C27CA": "Approchez vos mains de la tête de la cible neutralisée",
			"737D46D9": "Appuyez sur {SHOOT} pour lui briser le cou",
			"B332DDDF": "Bougez la tête pour regarder autour de vous",
			"5EF261AF": "Regarder autour de vous",
			"996F6909": "Prendre",
			"899158B0": "Appuyez sur {PICKUP} pour prendre la clé",
			"C9674DC9": "Frappez avec la clé préparée pour neutraliser le garde",
			"A18FE02F": "Neutraliser",
			"39A089AD": "Déplacer un corps",
			"77F9744E": "Approchez vos mains du corps et appuyez sur {PICKUP} pour le tirer",
			"56482D73": "Se débarrasser d'un corps",
			"F00E6306": "Approchez vos mains du placard et appuyez sur {PICKUP} pour y cacher le corps que vous avez traîné",
			"11740956": "Appuyez sur {PICKUP} pour prendre le pistolet",
			"DAD82FB5": "Prendre",
			"0BD5A6CD": "Prendre",
			"6E54917D": "Appuyez sur {PICKUP} pour prendre la mitraillette",
			"C50BFEAB": "Tirer sur le vase",
			"FE1F667A": "Regardez dans le viseur et tirez sur le vase",
			"EAC025F8": "Aide à la visée",
			"E29EB3CE": "Appuyez légèrement sur {SHOOT} pour activer l'aide à la visée",
			"6F619B07": "Tirer",
			"A5E8FFF9": "Touchez le cube 3 fois",
			"4A428E9E": "Appuyez sur {PICKUP} pour prendre le fusil de précision",
			"F8FEFD50": "Prendre",
			"2BAC2A10": "Lunette de fusil de précision",
			"864695A6": "Montez la manette vers votre tête pour regarder à travers la lunette",
			"8C0AF88C": "Bougez la manette pour viser la cible avec le fusil de précision",
			"4C45720E": "Fusil de précision",
			"034AB547": "Éliminez 3 cibles avec le fusil de précision",
			"21EBCDAA": "Lâcher",
			"E81F1E76": "Éloignez la manette de votre tête et appuyez sur {PICKUP} pour lâcher le fusil",
			"1903D3D1": "Éloignez la manette de votre tête pour quitter la visée dans la lunette",
			"1835D42E": "Viser au fusil de précision",
			"537E9ABE": "Donner un coup de poing",
			"A8E1B692": "Bougez la manette sans fil après avoir préparé votre poing pour neutraliser le garde",
			"AEAFC0F6": "Prendre",
			"C5A740C1": "Appuyez sur {PICKUP} pour prendre le katana",
			"898E8954": "Trancher",
			"D79106A2": "Bougez la manette après avoir préparé votre katana pour éliminer le garde",
			"31D90D85": "Préparation",
			"DE2548C2": "Maintenez {SHOOT} pour préparer le katana",
			"D4F3DA8F": "Ranger",
			"E7571AAF": "Placez votre main dans l'orbe devant votre poitrine",
			"33676692": "Appuyez sur {PICKUP} pour ranger",
			"32035A8B": "Appuyez sur {PICKUP} pour lâcher",
			"36FB842F": "En VR, l'orbe situé devant votre poitrine est l'endroit où vous rangez les objets et d'où vous les sortez.",
			"8245B103": "Appuyez sur {PICKUP} pour prendre",
			"E126213F": "Montez la caméra vers votre tête et visez le verrou de la fenêtre pour scanner",
			"C637A07E": "Montez la caméra vers votre tête et visez le corps pour scanner",
			"073EFDA0": "Faites pivoter votre main droite pour afficher la tenue actuellement portée et l'état",
			"0EF7F6D7": "Appuyez sur {HOLSTER} pour zoomer et sur {DROP} pour dézoomer",
			"AC030C7B": "Zoomer avec la lunette",
			"4A7FFCE5": "Placez votre main dans l'orbe devant votre poitrine et appuyez sur {PICKUP} pour ranger l'arme",
			"795D2E4D": "Ranger",
			"48E79F88": "Bougez la manette pour viser et appuyez sur {SHOOT} pour tirer",
			"7C815C56": "Maintenez {INSTINCT} pour utiliser votre instinct",
			"74D69893": "Appuyez sur {INSTINCT} pour utiliser votre instinct",
			"CEAB1B0E": "Maintenez {SHOOT} pour préparer",
			"629CB8A0": "Les gardes voient en vous une menace et veulent vous arrêter. Vous pouvez lever les bras pour faire semblant de vous rendre et laisser le garde s'approcher pour le surprendre au corps à corps, ou bien vous enfuir.",
			"3D2F2356": "Approchez vos mains de votre poitrine et appuyez sur {PICKUP} pour ranger les objets",
			"9F0007BD": "Le jeu sauvegardera automatiquement durant la partie.<br>Vous pouvez sauvegarder et charger manuellement à partir du menu.",
			"D43865ED": "Le jeu ne sauvegarde pas automatiquement quand vous jouez en VR.<BR>Vous pouvez sauvegarder et charger manuellement à partir du menu. Appuyez sur {START} pour accéder au menu.",
			"6D895B31": "Appuyez sur {PREVIOUS_ITEM} pour ouvrir l'inventaire et équiper la pièce",
			"2FF06C31": "Appuyez sur {PREVIOUS_ITEM} ou {NEXT_ITEM} pour ouvrir l'inventaire et équiper la pièce",
			"EBB0B836": "Inventaire",
			"3B7DB31A": "Appuyez sur {PICKUP} pour sortir un objet",
			"DEAE1211": "Appuyez sur {PICKUP} pour ranger",
			"B4DD0057": "Appuyez sur {PICKUP} pour ranger",
			"E6D45031": "Appuyez sur {PICKUP} pour sortir un objet",
			"B87E123B": "",
			"FA0E0149": "Placez votre main dans l'orbe devant votre poitrine et appuyez sur {PICKUP} pour sortir la pièce",
			"C9AAC169": "Sortir un objet",
			"252F7D35": "Lâcher",
			"E8D7842A": "Lâchez la mitraillette sur la table en appuyant sur {PICKUP}",
			"53971DD0": "Placer",
			"A01CEAE9": "Tendez le bras en avant et appuyez sur {PICKUP} pour lâcher l'objet",
			"0D9BFEF0": "Maintenez {START} pour réinitialiser votre position",
			"CFB4BF55": "Recentrer",
			"21D05080": "Recharger",
			"370D228E": "Appuyez sur {ACTION-Y} pour recharger votre arme à feu",
			"24918A76": "Appuyez sur {RELOAD} pour recharger votre arme à feu",
			"1FA146C9": "Appuyez sur {ACTION} pour ouvrir la porte",
			"5B6818D9": "Vous pouvez aussi ouvrir les portes en les touchant de la main.",
			"0278B54C": "Portes",
			"DEDCB3DE": "Appuyez sur {CROUCH} pour vous lever",
			"C683B297": "Furtif",
			"57F92367": "Se lever",
			"921350B3": "Maintenez {SHOOT} pour préparer la clé"
		},
		"it": {
			"D27065E2": "Questo è il Tutorial VR di Hitman.<br><br>Qui imparerai le basi per giocare a Hitman in VR.",
			"75CC9B46": "",
			"FD6F166C": "Questo è il campo di gioco VR. <br><br>Qui potrai familiarizzare con i diversi tipi di armi presenti nel gioco e fare pratica nello sparare e nel combattimento. <br><br>Premi il tasto di uscita quando vuoi uscire.",
			"D33D60AD": "Armi da fuoco",
			"DF50FC53": "",
			"9D0EED74": "Attivazione",
			"08B4B92C": "Quando giochi in VR, devi attivare gli oggetti per poter infliggere danni con essi. Tieni premuto {SHOOT} per attivare l'oggetto equipaggiato.",
			"D9A7D201": "Comfort VR",
			"59E44040": "Quando giochi in VR, puoi modificare la tua esperienza regolando le impostazioni di Comfort VR.<br><br>Sperimenta le varie impostazioni mentre giochi per trovare quelle che fanno al caso tuo.",
			"1AD1C70C": "Raccogli tutte le monete e riponile",
			"62BE6D2E": "Muovi la testa per guardare le sfere",
			"C394DB78": "Guardati attorno",
			"A31B1643": "Movimento",
			"D843821F": "Usa {MOVE} per muoverti",
			"ABD38F06": "Muovi {CAMERA} per girarti",
			"3E9F3799": "Girati",
			"7655B170": "Spara",
			"240319A6": "Premi {SHOOT} per sparare con l'arma",
			"CAE8EAB0": "Tieni premuto {AIM} per mirare con l'oggetto",
			"D8B9E452": "Muovi il controller per mirare con l'oggetto",
			"6A184CA1": "Lancia",
			"A7F5548B": "Premi {SHOOT} per lanciare l'oggetto",
			"761163D4": "Muovi la testa verso il basso per nasconderti dietro una copertura",
			"139474EA": "Coperture",
			"9A77C67E": "Premi {PICKUP} per raccogliere il cavo di fibra",
			"74EA7072": "Raccogli",
			"6671F5BB": "Attiva un oggetto corpo a corpo",
			"8A2A959F": "Tieni premuto {SHOOT} per attivare l'arma corpo a corpo equipaggiata",
			"92FA8413": "Tieni premuto {SHOOT} per stringere un pugno quando sei a mani vuote",
			"4E4E6836": "Attiva il pugno",
			"632CCAC2": "Tieni premuto {TAKE_DISGUISE} per interagire",
			"B77AB613": "Interagisci",
			"63BE8BF6": "Rimani immobile",
			"3D0EF624": "Vai in posizione",
			"DFD45FC7": "",
			"535E1038": "Tieni premuto {SHOOT} per attivare il cavo di fibra",
			"E56FDBEE": "Attiva il cavo di fibra",
			"50CA5C11": "Eliminazione con il cavo di fibra",
			"03395FD3": "Cavo di fibra",
			"D45247EE": "Muovi il cavo di fibra attivato sopra la testa del bersaglio e tira forte per eliminarlo",
			"BF7EF725": "Muovi le mani verso il collo",
			"ECE52B82": "Scuoti il controller per stordire più rapidamente",
			"1C48D01A": "Premi {SHOOT} per stordire",
			"F31131FF": "Tieni premuto {SHOOT} per stringere un pugno e muovi il controller per tirare un pugno",
			"8400C3CD": "Stordisci",
			"85CF62CC": "Posizionati nel cerchio",
			"FCED7DC9": "Spezza il collo",
			"CF6C27CA": "Muovi le mani verso la testa del bersaglio neutralizzato",
			"737D46D9": "Premi {SHOOT} per spezzare il collo",
			"B332DDDF": "Muovi la testa per guardarti attorno",
			"5EF261AF": "Guardati attorno",
			"996F6909": "Raccogli",
			"899158B0": "Premi {PICKUP} per raccogliere la chiave inglese",
			"C9674DC9": "Colpisci con la chiave inglese attivata per neutralizzare la guardia",
			"A18FE02F": "Neutralizza",
			"39A089AD": "Trascina il corpo",
			"77F9744E": "Muovi le mani verso il corpo e premi {PICKUP} per trascinarlo",
			"56482D73": "Occulta il corpo",
			"F00E6306": "Muovi le mani verso l'armadio e premi {PICKUP} per occultare il corpo che stavi trascinando",
			"11740956": "Premi {PICKUP} per raccogliere la pistola",
			"DAD82FB5": "Raccogli",
			"0BD5A6CD": "Raccogli",
			"6E54917D": "Premi {PICKUP} per raccogliere il mitra",
			"C50BFEAB": "Spara al vaso",
			"FE1F667A": "Guarda attraverso il mirino per mirare e spara al vaso",
			"EAC025F8": "Mira assistita",
			"E29EB3CE": "Premi leggermente {SHOOT} per attivare la mira assistita",
			"6F619B07": "Spara",
			"A5E8FFF9": "Colpisci il cubo tre volte",
			"4A428E9E": "Premi {PICKUP} per raccogliere il fucile di precisione",
			"F8FEFD50": "Raccogli",
			"2BAC2A10": "Mirino telescopico",
			"864695A6": "Muovi il controller in alto verso la tua testa per accedere al mirino telescopico",
			"8C0AF88C": "Muovi il controller per mirare un bersaglio con il mirino telescopico",
			"4C45720E": "Fucile di precisione",
			"034AB547": "Elimina tre bersagli con il fucile di precisione",
			"21EBCDAA": "Lascia",
			"E81F1E76": "Muovi il controller lontano dalla testa e premi {PICKUP} per lasciare il fucile",
			"1903D3D1": "Muovi il controller lontano dalla testa per uscire dal mirino telescopico",
			"1835D42E": "Mira di precisione",
			"537E9ABE": "Tira un pugno",
			"A8E1B692": "Muovi il controller wireless quando il pugno è attivato per neutralizzare la guardia",
			"AEAFC0F6": "Raccogli",
			"C5A740C1": "Premi {PICKUP} per raccogliere la katana",
			"898E8954": "Esegui un fendente",
			"D79106A2": "Muovi il controller quando la katana è attivata per eliminare la guardia",
			"31D90D85": "Attivazione",
			"DE2548C2": "Tieni premuto {SHOOT} per attivare la katana",
			"D4F3DA8F": "Rinfoderare",
			"E7571AAF": "Muovi la mano nella sfera del petto",
			"33676692": "Premi {PICKUP} per rinfoderare",
			"32035A8B": "Premi {PICKUP} per lasciare",
			"36FB842F": "In VR, la sfera di fronte al tuo petto è dove puoi rinfoderare ed estrarre gli oggetti.",
			"8245B103": "Premi {PICKUP} per raccogliere",
			"E126213F": "Muovi la telecamera in alto verso la testa e mira alla serratura della finestra per scansionarlo",
			"C637A07E": "Muovi la telecamera in alto verso la testa e mira al corpo per scansionarlo",
			"073EFDA0": "Ruota la mano destra per vedere il tuo travestimento attuale e il tuo stato",
			"0EF7F6D7": "Premi {HOLSTER} per zoomare in avanti e {DROP} per zoomare all'indietro",
			"AC030C7B": "Zoom del mirino telescopico",
			"4A7FFCE5": "Muovi la mano nella sfera del petto e premi {PICKUP} per rinfoderare l'arma",
			"795D2E4D": "Rinfoderare",
			"48E79F88": "Muovi il controller per mirare, premi {SHOOT} per sparare",
			"7C815C56": "Tieni premuto {INSTINCT} per attivare l'istinto",
			"74D69893": "Premi {INSTINCT} per attivare l'istinto",
			"CEAB1B0E": "Tieni premuto {SHOOT} per attivare",
			"629CB8A0": "Le guardie ti considerano una minaccia e vogliono arrestarti. Puoi simulare la resa alzando le mani verso l'alto e attirare la guardia più vicino, creando un'opportunità per attaccarla o per fuggire.",
			"3D2F2356": "Muovi la mano verso il petto e premi {PICKUP} per rinfoderare gli oggetti",
			"9F0007BD": "Il gioco salva automaticamente durante la partita.<BR>Puoi salvare e caricare manualmente dal menu.",
			"D43865ED": "Il gioco non salva automaticamente quando giochi in VR.<BR>Puoi salvare e caricare manualmente dal menu. Premi {START} per accedere al menu.",
			"6D895B31": "Premi {PREVIOUS_ITEM} per aprire l'inventario ed equipaggiare una moneta",
			"2FF06C31": "Premi {PREVIOUS_ITEM} o {NEXT_ITEM} per aprire l'inventario ed equipaggiare la moneta",
			"EBB0B836": "Inventario",
			"3B7DB31A": "Premi {PICKUP} per estrarre",
			"DEAE1211": "Premi {PICKUP} per rinfoderare",
			"B4DD0057": "Premi {PICKUP} per rinfoderare",
			"E6D45031": "Premi {PICKUP} per estrarre",
			"B87E123B": "",
			"FA0E0149": "Muovi la mano nella sfera del petto e premi {PICKUP} per estrarre la moneta",
			"C9AAC169": "Estrai",
			"252F7D35": "Lascia",
			"E8D7842A": "Lascia il mitra sul tavolo premendo {PICKUP}",
			"53971DD0": "Posiziona",
			"A01CEAE9": "Distendi le braccia lontano dal petto e premi {PICKUP} per lasciare l'oggetto",
			"0D9BFEF0": "Tieni premuto {START} per azzerare la tua posizione",
			"CFB4BF55": "Ricentra",
			"21D05080": "Ricarica",
			"370D228E": "Premi {ACTION-Y} per ricaricare la tua arma da fuoco",
			"24918A76": "Premi {RELOAD} per ricaricare la tua arma da fuoco",
			"1FA146C9": "Apri la porta premendo {ACTION}",
			"5B6818D9": "Puoi aprire le porte anche toccandole con la mano",
			"0278B54C": "Porte",
			"DEDCB3DE": "Premi {CROUCH} per alzarti",
			"C683B297": "Furtività",
			"57F92367": "Alzati",
			"921350B3": "Tieni premuto {SHOOT} per attivare la chiave inglese"
		},
		"de": {
			"D27065E2": "Willkommen beim VR-Tutorial von Hitman.<br><br>Hier erlernen Sie die Grundlagen, wie man Hitman in der VR spielt.",
			"75CC9B46": "",
			"FD6F166C": "Willkommen auf dem VR-Spielplatz.<br><br>Verbringen Sie etwas Zeit hier, um sich mit unterschiedlichen Nah- und Fernkampfwaffen sowie dem Schlagen und Schießen vertraut zu machen.<br><br>Drücken Sie die Verlassen-Taste, sobald Sie bereit sind, von hier wieder aufzubrechen.",
			"D33D60AD": "Feuerwaffen",
			"DF50FC53": "",
			"9D0EED74": "Bereit machen",
			"08B4B92C": "Wenn Sie in der VR spielen, müssen Sie Gegenstände bereit machen, um mit Ihnen Schaden zufügen zu können. Halten Sie {SHOOT} gedrückt, um den aktuell ausgerüsteten Gegenstand bereit zu machen.",
			"D9A7D201": "VR-Komfort",
			"59E44040": "Wenn Sie in der VR spielen, können Sie Ihre Erfahrung durch die VR-Komfort-Einstellungen anpassen.<br><br>Experimentieren Sie mit den Einstellungen, um herauszufinden, was am besten zu Ihnen passt.",
			"1AD1C70C": "Heben Sie alle Münzen auf und stecken Sie sie weg.",
			"62BE6D2E": "Bewegen Sie den Kopf und schauen Sie die Kugeln an.",
			"C394DB78": "Schauen Sie sich um.",
			"A31B1643": "Bewegen",
			"D843821F": "Verwenden Sie {MOVE}, um sich zu bewegen.",
			"ABD38F06": "Verwenden Sie {CAMERA}, um sich zu drehen.",
			"3E9F3799": "Drehen",
			"7655B170": "Schießen",
			"240319A6": "Drücken Sie {SHOOT}, um mit einer Waffe zu feuern.",
			"CAE8EAB0": "Halten Sie {AIM} gedrückt, um das Zielen mit einem Gegenstand zu aktivieren.",
			"D8B9E452": "Bewegen Sie den Controller, um mit einem Gegenstand zu zielen.",
			"6A184CA1": "Werfen",
			"A7F5548B": "Drücken Sie {SHOOT}, um einen Gegenstand zu werfen.",
			"761163D4": "Bewegen Sie den Kopf nach unten, um in Deckung zu gehen.",
			"139474EA": "Deckung",
			"9A77C67E": "Halten Sie {PICKUP} gedrückt, um die Klaviersaite zu nehmen.",
			"74EA7072": "Nehmen",
			"6671F5BB": "Nahkampfgegenstand bereit machen",
			"8A2A959F": "Halten Sie {SHOOT} gedrückt, um eine ausgerüstete Nahkampfwaffe scharfzumachen.",
			"92FA8413": "Halten Sie {SHOOT} gedrückt, um mit leeren Händen die Fäuste zu ballen.",
			"4E4E6836": "Faust bereit machen",
			"632CCAC2": "Halten Sie {TAKE_DISGUISE} gedrückt, um zu interagieren.",
			"B77AB613": "Interagieren",
			"63BE8BF6": "Still stehen bleiben",
			"3D0EF624": "In Stellung gehen",
			"DFD45FC7": "",
			"535E1038": "Halten Sie {SHOOT} gedrückt, um die Klaviersaite bereit zu machen.",
			"E56FDBEE": "Klaviersaite bereit machen",
			"50CA5C11": "Eliminieren mit der Klaviersaite",
			"03395FD3": "Klaviersaite",
			"D45247EE": "Bewegen Sie die bereit gemachte Klaviersaite über den Kopf des Ziels und ziehen Sie fest zu, um es auszuschalten.",
			"BF7EF725": "Greifen Sie mit der Hand um den Hals.",
			"ECE52B82": "Schütteln Sie den Controller, um das Ziel schneller zu überwältigen.",
			"1C48D01A": "Drücken Sie {SHOOT} zum Überwältigen.",
			"F31131FF": "Halten Sie {SHOOT} gedrückt, um eine Faust zu ballen, und bewegen Sie den Controller, um zuzuschlagen.",
			"8400C3CD": "Überwältigen",
			"85CF62CC": "Gehen Sie in den Kreis.",
			"FCED7DC9": "Genick brechen",
			"CF6C27CA": "Bewegen Sie die Hände nach vorn, um ein Ziel ruhigzustellen.",
			"737D46D9": "Drücken Sie {SHOOT}, um das Genick zu brechen.",
			"B332DDDF": "Bewegen Sie den Kopf, um sich umzuschauen.",
			"5EF261AF": "Schauen Sie sich um.",
			"996F6909": "Nehmen",
			"899158B0": "Drücken Sie {PICKUP}, um den Schraubenschlüssel zu nehmen.",
			"C9674DC9": "Schlagen Sie mit dem Schraubenschlüssel zu, um die Wache ruhigzustellen.",
			"A18FE02F": "Ruhigstellen",
			"39A089AD": "Körper wegschleifen",
			"77F9744E": "Strecken Sie die Hände in Richtung des Körpers aus und drücken Sie {PICKUP}, um ihn wegzuschleifen.",
			"56482D73": "Körper ablegen",
			"F00E6306": "Strecken Sie die Hände in Richtung des Schranks aus und drücken Sie {PICKUP}, um den Körper zu verstecken.",
			"11740956": "Drücken Sie {PICKUP}, um die Pistole zu nehmen.",
			"DAD82FB5": "Nehmen",
			"0BD5A6CD": "Nehmen",
			"6E54917D": "Drücken Sie {PICKUP}, um die Maschinenpistole zu nehmen.",
			"C50BFEAB": "Auf Vase schießen",
			"FE1F667A": "Schauen Sie durch das Visier und schießen Sie auf die Vase.",
			"EAC025F8": "Zielunterstützung",
			"E29EB3CE": "Drücken Sie kurz {SHOOT}, um die Zielunterstützung zu aktivieren.",
			"6F619B07": "Schießen",
			"A5E8FFF9": "Treffen Sie dreimal den Würfel.",
			"4A428E9E": "Drücken Sie {PICKUP}, um das Scharfschützengewehr zu nehmen.",
			"F8FEFD50": "Nehmen",
			"2BAC2A10": "Zielfernrohr",
			"864695A6": "Bewegen Sie den Controller nach oben in Richtung des Kopfs, um in den Zielfernrohr-Modus zu gehen.",
			"8C0AF88C": "Bewegen Sie den Controller, um mit dem Zielfernrohr das Ziel anzuvisieren.",
			"4C45720E": "Scharfschützengewehr",
			"034AB547": "Eliminieren Sie drei Ziele mit dem Scharfschützengewehr.",
			"21EBCDAA": "Fallen lassen",
			"E81F1E76": "Bewegen Sie den Controller weg vom Kopf und drücken Sie {PICKUP}, um das Gewehr fallen zu lassen.",
			"1903D3D1": "Bewegen Sie den Controller weg vom Kopf, um den Zielfernrohr-Modus zu verlassen.",
			"1835D42E": "Scharfschützenzielen",
			"537E9ABE": "Schlag",
			"A8E1B692": "Bewegen Sie den Wireless-Controller mit bereit gemachter Faust, um Wachen ruhigzustellen.",
			"AEAFC0F6": "Nehmen",
			"C5A740C1": "Drücken Sie {PICKUP}, um das Katana zu nehmen.",
			"898E8954": "Hieb",
			"D79106A2": "Bewegen Sie den Controller mit bereit gemachtem Katana, um Wachen zu töten.",
			"31D90D85": "Bereit machen",
			"DE2548C2": "Halten Sie {SHOOT} gedrückt, um das Katana bereit zu machen.",
			"D4F3DA8F": "Wegstecken",
			"E7571AAF": "Bewegen Sie die Hand in die Kugel an der Brust.",
			"33676692": "Drücken Sie {PICKUP}, um eine Waffe wegzustecken.",
			"32035A8B": "Drücken Sie {PICKUP} zum Fallenlassen.",
			"36FB842F": "In der VR wird Ihre Waffe aus der Kugel vor der Brust hervorgeholt und auch dort verstaut.",
			"8245B103": "Drücken Sie {PICKUP} zum Nehmen.",
			"E126213F": "Bewegen Sie die Kamera nach oben zum Kopf und zielen Sie auf das Fensterschloss, um es zu scannen.",
			"C637A07E": "Bewegen Sie die Kamera nach oben zum Kopf und zielen Sie auf den Körper, um ihn zu scannen.",
			"073EFDA0": "Drehen Sie die rechte Hand, um Outfit und Status zu sehen.",
			"0EF7F6D7": "Drücken Sie {HOLSTER} zum Heranzoomen oder {DROP} zum Herauszoomen.",
			"AC030C7B": "Zielfernrohr-Zoom",
			"4A7FFCE5": "Bewegen Sie die Hand in die Kugel an der Brust und drücken Sie {PICKUP}, um die Waffe wegzustecken.",
			"795D2E4D": "Wegstecken",
			"48E79F88": "Bewegen Sie den Controller zum Zielen; drücken Sie {SHOOT} zum Schießen.",
			"7C815C56": "Halten Sie {INSTINCT} gedrückt, um Instinkt zu aktivieren.",
			"74D69893": "Drücken Sie {INSTINCT}, um Instinkt zu aktivieren.",
			"CEAB1B0E": "Halten Sie {SHOOT} gedrückt, um etwas bereit zu machen.",
			"629CB8A0": "Die Wachen betrachten Sie als Bedrohung und versuchen, Sie festzunehmen. Täuschen Sie vor, dass Sie sich ergeben, indem Sie die Hände heben und die Wache herankommen lassen. Dann haben Sie die Gelegenheit, anzugreifen oder wegzulaufen.",
			"3D2F2356": "Bewegen Sie die Hand zur Brust und drücken Sie {PICKUP}, um die Waffe wegzustecken.",
			"9F0007BD": "Das Spiel speichert automatisch.<BR>Sie können im Menü manuell speichern und laden.",
			"D43865ED": "Das Spiel speichert beim VR-Spiel nicht automatisch.<BR>Sie können im Menü manuell speichern und laden. Drücken Sie {START}, um ins Menü zu kommen.",
			"6D895B31": "Drücken Sie {PREVIOUS_ITEM}, um das Inventar zu öffnen und Münzen auszurüsten.",
			"2FF06C31": "Drücken Sie {PREVIOUS_ITEM} oder {NEXT_ITEM}, um das Inventar zu öffnen und Münzen auszurüsten.",
			"EBB0B836": "Inventar",
			"3B7DB31A": "Drücken Sie {PICKUP} zum Ziehen.",
			"DEAE1211": "Drücken Sie {PICKUP} zum Wegstecken.",
			"B4DD0057": "Drücken Sie {PICKUP} zum Wegstecken.",
			"E6D45031": "Drücken Sie {PICKUP} zum Ziehen.",
			"B87E123B": "",
			"FA0E0149": "Bewegen Sie die Hand in die Kugel an der Brust und drücken Sie {PICKUP}, um die Münzen wegzustecken.",
			"C9AAC169": "Rausholen",
			"252F7D35": "Fallen lassen",
			"E8D7842A": "Drücken Sie {PICKUP}, um die Maschinenpistole auf den Tisch fallen zu lassen.",
			"53971DD0": "Hinlegen",
			"A01CEAE9": "Strecken Sie den Arm aus drücken Sie {PICKUP}, um einen Gegenstand fallen zu lassen.",
			"0D9BFEF0": "Halten Sie {START} gedrückt, um Ihre Position zurückzusetzen.",
			"CFB4BF55": "Neu zentrieren",
			"21D05080": "Nachladen",
			"370D228E": "Drücken Sie {ACTION-Y}, um Ihre Feuerwaffe nachzuladen.",
			"24918A76": "Drücken Sie {RELOAD}, um Ihre Feuerwaffe nachzuladen.",
			"1FA146C9": "Drücken Sie {ACTION}, um die Tür zu öffnen.",
			"5B6818D9": "Sie können Türen öffnen, wenn Sie sie mit der Hand berühren.",
			"0278B54C": "Türen",
			"DEDCB3DE": "Drücken Sie {CROUCH}, um aufzustehen.",
			"C683B297": "Ducken",
			"57F92367": "Aufstehen",
			"921350B3": "Halten Sie {SHOOT} gedrückt, um den Schraubenschlüssel bereit zu machen."
		},
		"es": {
			"D27065E2": "Te damos la bienvenida al tutorial de realidad virtual de Hitman.<br><br>Aquí aprenderás lo básico para jugar a Hitman en RV.",
			"75CC9B46": "",
			"FD6F166C": "Esta es la zona de recreo de RV. <br><br>Pasa tiempo aquí para familiarizarte con distintas armas de fuego y de otra índole, y practica disparando y zurrando. <br><br>Pulsa el botón Salir cuando quieras dejarlo.",
			"D33D60AD": "Armas de fuego",
			"DF50FC53": "",
			"9D0EED74": "Preparado",
			"08B4B92C": "Cuando juegues en RV, tienes que preparar los objetos para poder hacer más daño con ellos. Mantén {SHOOT} para preparar el objeto que tengas equipado en ese momento.",
			"D9A7D201": "Confort de RV",
			"59E44040": "Al jugar en RV, puedes afinar tu experiencia configurando los Ajustes de confort de RV.<br><br>Prueba los ajustes mientras juegas hasta encontrar lo que mejor se adapte a ti.",
			"1AD1C70C": "Recoge todas las monedas y guárdatelas",
			"62BE6D2E": "Mueve la cabeza para mirar los orbes",
			"C394DB78": "Mirar alrededor",
			"A31B1643": "Movimiento",
			"D843821F": "Usa {MOVE} para moverte",
			"ABD38F06": "Mueve {CAMERA} para girar",
			"3E9F3799": "Girarse",
			"7655B170": "Disparar",
			"240319A6": "Pulsa {SHOOT} para disparar el arma",
			"CAE8EAB0": "Mantén {AIM} para activar la mira",
			"D8B9E452": "Mueve el mando para apuntar a un objeto",
			"6A184CA1": "Lanzamiento",
			"A7F5548B": "Pulsa {SHOOT} para lanzar el objeto",
			"761163D4": "Baja la cabeza para ponerte a cubierto",
			"139474EA": "Coberturas",
			"9A77C67E": "Pulsa {PICKUP} para recoger el cable de fibra",
			"74EA7072": "Recoger",
			"6671F5BB": "Blandir objeto contundente",
			"8A2A959F": "Mantén {SHOOT} para blandir el arma cuerpo a cuerpo que tengas equipada",
			"92FA8413": "Mantén {SHOOT} para cerrar el puño cuando no tengas nada en las manos",
			"4E4E6836": "Cerrar el puño",
			"632CCAC2": "Mantén {TAKE_DISGUISE} para interactuar",
			"B77AB613": "Interactuar",
			"63BE8BF6": "No te muevas",
			"3D0EF624": "Ponte en posición",
			"DFD45FC7": "",
			"535E1038": "Mantén {SHOOT} para tensar el cable de fibra",
			"E56FDBEE": "Tensar cable de fibra",
			"50CA5C11": "Eliminación con cable de fibra",
			"03395FD3": "Cable de fibra",
			"D45247EE": "Pasa el cable de fibra tensado por encima de la cabeza del objetivo y tira fuerte para eliminarlo",
			"BF7EF725": "Extiende la mano hacia el cuello",
			"ECE52B82": "Sacude el mando para dejarlo inconsciente",
			"1C48D01A": "Pulsa {SHOOT} para dejarlo inconsciente",
			"F31131FF": "Mantén {SHOOT} para cerrar el puño y mueve el mando para dar un puñetazo",
			"8400C3CD": "Dejar inconsciente",
			"85CF62CC": "Ponte en el círculo",
			"FCED7DC9": "Romper cuellos",
			"CF6C27CA": "Mueve las manos hacia la cabeza del objetivo inconsciente",
			"737D46D9": "Pulsa {SHOOT} para romperle el cuello",
			"B332DDDF": "Mueve la cabeza alrededor para mirar",
			"5EF261AF": "Mirar alrededor",
			"996F6909": "Recoger",
			"899158B0": "Pulsa {PICKUP} para recoger la llave",
			"C9674DC9": "Mueve el mando cuando estés blandiendo la llave inglesa para dejar inconsciente al guardia",
			"A18FE02F": "Dejar inconsciente",
			"39A089AD": "Arrastrar cuerpo",
			"77F9744E": "Extiende la mano hacia el cuerpo y pulsa {PICKUP} para arrastrarlo",
			"56482D73": "Deshacerse del cuerpo",
			"F00E6306": "Extiende la mano hacia el armario y pulsa {PICKUP} para tirar dentro el cuerpo que arrastras",
			"11740956": "Pulsa {PICKUP} para recoger la pistola",
			"DAD82FB5": "Recoger",
			"0BD5A6CD": "Recoger",
			"6E54917D": "Pulsa {PICKUP} para recoger el subfusil",
			"C50BFEAB": "Disparar al jarrón",
			"FE1F667A": "Apunta por la mira y dispara al jarrón",
			"EAC025F8": "Puntería asistida",
			"E29EB3CE": "Presiona {SHOOT} ligeramente para activar la puntería asistida",
			"6F619B07": "Disparar",
			"A5E8FFF9": "Acierta tres veces al cubo",
			"4A428E9E": "Pulsa {PICKUP} para recoger el fusil de francotirador",
			"F8FEFD50": "Recoger",
			"2BAC2A10": "Mira de francotirador",
			"864695A6": "Sube el mando hacia la cabeza para ver por la mira de francotirador",
			"8C0AF88C": "Mueve el mando alrededor para apuntar al objetivo por la mira de francotirador",
			"4C45720E": "Francotirador",
			"034AB547": "Elimina tres objetivos con el fusil de francotirador",
			"21EBCDAA": "Soltar",
			"E81F1E76": "Aléjate el mando de la cabeza y pulsa {PICKUP} para soltar el fusil",
			"1903D3D1": "Aléjate el mando de la cabeza para salir de la mira",
			"1835D42E": "Apuntar con fusil de francotirador",
			"537E9ABE": "Puñetazo",
			"A8E1B692": "Mueve el mando inalámbrico cuando el puño esté cerrado para dejar inconsciente al guardia",
			"AEAFC0F6": "Recoger",
			"C5A740C1": "Pulsa  {PICKUP} para recoger la katana",
			"898E8954": "Dar tajos",
			"D79106A2": "Mueve el mando cuando estés blandiendo la katana para matar al guardia",
			"31D90D85": "Blandiendo",
			"DE2548C2": "Mantén {SHOOT} para blandir la katana",
			"D4F3DA8F": "Enfundar",
			"E7571AAF": "Mete la mano en el orbe del pecho",
			"33676692": "Pulsa {PICKUP} para enfundar",
			"32035A8B": "Pulsa {PICKUP} para soltar",
			"36FB842F": "En RV, el orbe que tienes delante del pecho sirve para guardar y sacar objetos.",
			"8245B103": "Pulsa {PICKUP} para recoger",
			"E126213F": "Sube la cámara hacia la cabeza y apunta a la cerradura de la ventana para escanearla",
			"C637A07E": "Sube la cámara hacia la cabeza y apunta al cuerpo para escanearlo",
			"073EFDA0": "Gira la mano derecha para ver el atuendo que llevas y la situación",
			"0EF7F6D7": "Pulsa {HOLSTER} para acercar la vista y {DROP} para alejarla",
			"AC030C7B": "Zoom con mira",
			"4A7FFCE5": "Mete la mano en el orbe del pecho y pulsa {PICKUP} para enfundar el arma",
			"795D2E4D": "Enfundar",
			"48E79F88": "Mueve el mando para apuntar, pulsa {SHOOT} para disparar.",
			"7C815C56": "Mantén {INSTINCT} para activar el Instinto.",
			"74D69893": "Pulsa {INSTINCT} para activar el Instinto.",
			"CEAB1B0E": "Mantén {SHOOT} para prepararte",
			"629CB8A0": "Los guardias te consideran una amenaza y quieren arrestarte. Para hacer que obedeces, levanta las manos y atrae al guardia más cercano, así tendrás oportunidad de atacarlo y de escapar.",
			"3D2F2356": "Acerca la mano al pecho y pulsa {PICKUP} para guardar objetos",
			"9F0007BD": "El juego se guardará automáticamente durante la partida.<BR>Puedes cargar y guardar manualmente desde el menú.",
			"D43865ED": "Al jugar en RV, la partida no se guardará de manera automática.<BR>Puedes cargar y guardar manualmente desde el menú. Pulsa {START} para entrar en el menú.",
			"6D895B31": "Pulsa {PREVIOUS_ITEM} para abrir el inventario y equipar una moneda",
			"2FF06C31": "Pulsa {PREVIOUS_ITEM} o {NEXT_ITEM} para abrir el inventario y equipar una moneda",
			"EBB0B836": "Inventario",
			"3B7DB31A": "Pulsa {PICKUP} para desenfundar",
			"DEAE1211": "Pulsa {PICKUP} para enfundar",
			"B4DD0057": "Pulsa {PICKUP} para enfundar",
			"E6D45031": "Pulsa {PICKUP} para desenfundar",
			"B87E123B": "",
			"FA0E0149": "Mete la mano en el orbe del pecho y pulsa {PICKUP} para sacar una moneda",
			"C9AAC169": "Desenfundar",
			"252F7D35": "Soltar",
			"E8D7842A": "Para soltar el subfusil en una mesa, pulsa {PICKUP}",
			"53971DD0": "Colocar",
			"A01CEAE9": "Estira el brazo y pulsa {PICKUP} para soltar un objeto",
			"0D9BFEF0": "Mantén {START} para restablecer tu posición",
			"CFB4BF55": "Recentrar",
			"21D05080": "Recargar",
			"370D228E": "Pulsa {ACTION-Y} para recargar tu arma de fuego",
			"24918A76": "Pulsa {RELOAD} para recargar tu arma de fuego",
			"1FA146C9": "Para abrir la puerta, pulsa {ACTION}",
			"5B6818D9": "También puedes abrir puertas tocándolas con la mano",
			"0278B54C": "Puertas",
			"DEDCB3DE": "Pulsa {CROUCH}  para levantarte.",
			"C683B297": "Sigilo",
			"57F92367": "Levantarse",
			"921350B3": "Mantén {SHOOT} para blandir la llave inglesa"
		}
	}
}
